sag_reader/__init__.py
sag_reader/__main__.py
sag_reader-1.0.4.dist-info/LICENSE
sag_reader-1.0.4.dist-info/METADATA
sag_reader-1.0.4.dist-info/WHEEL
sag_reader-1.0.4.dist-info/entry_points.txt
sag_reader-1.0.4.dist-info/top_level.txt
sag_reader-1.0.4.dist-info/RECORD
