Metadata-Version: 2.1
Name: sag-reader
Version: 1.0.4
Summary: Python app to read CISA Software Acquisition Guide Spreadsheets based on CISA format https://cisa.gov/sag
Author-email: "Richard (Dick) Brooks" <dick@reliableenergyanalytics.com>, Joseph Wortmann <joseph.wortmann@gmail.com>
License: MIT License
Project-URL: Homepage, https://github.com/rjb4standards/CISASAGReader
Project-URL: Repository, https://github.com/rjb4standards/CISASAGReader.git
Project-URL: Issues, https://github.com/rjb4standards/CISASAGReader/issues
Keywords: Software Acquisition Guide,CISA,Secure by Design
Classifier: Development Status :: 5 - Production/Stable
Classifier: License :: OSI Approved :: MIT License
Classifier: Programming Language :: Python :: 3
Classifier: Programming Language :: Python :: 3.10
Classifier: Programming Language :: Python :: 3.11
Classifier: Programming Language :: Python :: 3.12
Classifier: Topic :: Utilities
Requires-Python: >=3.10
License-File: LICENSE
Requires-Dist: openpyxl==3.1.5
Requires-Dist: pandas==2.2.3
Requires-Dist: typer==0.15.1
Requires-Dist: xlrd==2.0.1
